{"moduleName":["Global"],"imports":[{"annotation":{"meta":null,"sourceSpan":{"start":[3,1],"end":[93,73]}},"moduleName":["Data","Function"]},{"annotation":{"meta":null,"sourceSpan":{"start":[3,1],"end":[93,73]}},"moduleName":["Data","Function","Uncurried"]},{"annotation":{"meta":null,"sourceSpan":{"start":[3,1],"end":[93,73]}},"moduleName":["Data","Maybe"]},{"annotation":{"meta":null,"sourceSpan":{"start":[3,1],"end":[93,73]}},"moduleName":["Global"]},{"annotation":{"meta":null,"sourceSpan":{"start":[19,1],"end":[19,15]}},"moduleName":["Prelude"]},{"annotation":{"meta":null,"sourceSpan":{"start":[3,1],"end":[93,73]}},"moduleName":["Prim"]}],"builtWith":"0.13.6","modulePath":".spago/globals/v4.1.0/src/Global.purs","exports":["nan","isNaN","infinity","isFinite","readInt","readFloat","toFixed","toExponential","toPrecision","decodeURI","encodeURI","decodeURIComponent","encodeURIComponent"],"decls":[{"annotation":{"meta":null,"sourceSpan":{"start":[64,1],"end":[64,45]}},"identifier":"toPrecision","expression":{"annotation":{"meta":null,"sourceSpan":{"start":[64,1],"end":[64,45]}},"body":{"annotation":{"meta":null,"sourceSpan":{"start":[64,1],"end":[64,45]}},"body":{"annotation":{"meta":null,"sourceSpan":{"start":[65,24],"end":[65,73]}},"argument":{"annotation":{"meta":null,"sourceSpan":{"start":[65,72],"end":[65,73]}},"value":{"moduleName":null,"identifier":"n"},"type":"Var"},"type":"App","abstraction":{"annotation":{"meta":null,"sourceSpan":{"start":[65,24],"end":[65,71]}},"argument":{"annotation":{"meta":null,"sourceSpan":{"start":[65,65],"end":[65,71]}},"value":{"moduleName":null,"identifier":"digits"},"type":"Var"},"type":"App","abstraction":{"annotation":{"meta":null,"sourceSpan":{"start":[65,24],"end":[65,64]}},"argument":{"annotation":{"meta":{"metaType":"IsConstructor","identifiers":["value0"],"constructorType":"SumType"},"sourceSpan":{"start":[65,60],"end":[65,64]}},"value":{"moduleName":["Data","Maybe"],"identifier":"Just"},"type":"Var"},"type":"App","abstraction":{"annotation":{"meta":null,"sourceSpan":{"start":[65,24],"end":[65,59]}},"argument":{"annotation":{"meta":null,"sourceSpan":{"start":[65,45],"end":[65,58]}},"argument":{"annotation":{"meta":{"metaType":"IsConstructor","identifiers":[],"constructorType":"SumType"},"sourceSpan":{"start":[65,51],"end":[65,58]}},"value":{"moduleName":["Data","Maybe"],"identifier":"Nothing"},"type":"Var"},"type":"App","abstraction":{"annotation":{"meta":{"metaType":"IsForeign"},"sourceSpan":{"start":[65,45],"end":[65,50]}},"value":{"moduleName":["Data","Function"],"identifier":"const"},"type":"Var"}},"type":"App","abstraction":{"annotation":{"meta":null,"sourceSpan":{"start":[65,24],"end":[65,43]}},"argument":{"annotation":{"meta":{"metaType":"IsForeign"},"sourceSpan":{"start":[65,31],"end":[65,43]}},"value":{"moduleName":["Global"],"identifier":"_toPrecision"},"type":"Var"},"type":"App","abstraction":{"annotation":{"meta":{"metaType":"IsForeign"},"sourceSpan":{"start":[65,24],"end":[65,30]}},"value":{"moduleName":["Data","Function","Uncurried"],"identifier":"runFn4"},"type":"Var"}}}}}},"argument":"n","type":"Abs"},"argument":"digits","type":"Abs"},"bindType":"NonRec"},{"annotation":{"meta":null,"sourceSpan":{"start":[50,1],"end":[50,41]}},"identifier":"toFixed","expression":{"annotation":{"meta":null,"sourceSpan":{"start":[50,1],"end":[50,41]}},"body":{"annotation":{"meta":null,"sourceSpan":{"start":[50,1],"end":[50,41]}},"body":{"annotation":{"meta":null,"sourceSpan":{"start":[51,20],"end":[51,65]}},"argument":{"annotation":{"meta":null,"sourceSpan":{"start":[51,64],"end":[51,65]}},"value":{"moduleName":null,"identifier":"n"},"type":"Var"},"type":"App","abstraction":{"annotation":{"meta":null,"sourceSpan":{"start":[51,20],"end":[51,63]}},"argument":{"annotation":{"meta":null,"sourceSpan":{"start":[51,57],"end":[51,63]}},"value":{"moduleName":null,"identifier":"digits"},"type":"Var"},"type":"App","abstraction":{"annotation":{"meta":null,"sourceSpan":{"start":[51,20],"end":[51,56]}},"argument":{"annotation":{"meta":{"metaType":"IsConstructor","identifiers":["value0"],"constructorType":"SumType"},"sourceSpan":{"start":[51,52],"end":[51,56]}},"value":{"moduleName":["Data","Maybe"],"identifier":"Just"},"type":"Var"},"type":"App","abstraction":{"annotation":{"meta":null,"sourceSpan":{"start":[51,20],"end":[51,51]}},"argument":{"annotation":{"meta":null,"sourceSpan":{"start":[51,37],"end":[51,50]}},"argument":{"annotation":{"meta":{"metaType":"IsConstructor","identifiers":[],"constructorType":"SumType"},"sourceSpan":{"start":[51,43],"end":[51,50]}},"value":{"moduleName":["Data","Maybe"],"identifier":"Nothing"},"type":"Var"},"type":"App","abstraction":{"annotation":{"meta":{"metaType":"IsForeign"},"sourceSpan":{"start":[51,37],"end":[51,42]}},"value":{"moduleName":["Data","Function"],"identifier":"const"},"type":"Var"}},"type":"App","abstraction":{"annotation":{"meta":null,"sourceSpan":{"start":[51,20],"end":[51,35]}},"argument":{"annotation":{"meta":{"metaType":"IsForeign"},"sourceSpan":{"start":[51,27],"end":[51,35]}},"value":{"moduleName":["Global"],"identifier":"_toFixed"},"type":"Var"},"type":"App","abstraction":{"annotation":{"meta":{"metaType":"IsForeign"},"sourceSpan":{"start":[51,20],"end":[51,26]}},"value":{"moduleName":["Data","Function","Uncurried"],"identifier":"runFn4"},"type":"Var"}}}}}},"argument":"n","type":"Abs"},"argument":"digits","type":"Abs"},"bindType":"NonRec"},{"annotation":{"meta":null,"sourceSpan":{"start":[57,1],"end":[57,47]}},"identifier":"toExponential","expression":{"annotation":{"meta":null,"sourceSpan":{"start":[57,1],"end":[57,47]}},"body":{"annotation":{"meta":null,"sourceSpan":{"start":[57,1],"end":[57,47]}},"body":{"annotation":{"meta":null,"sourceSpan":{"start":[58,26],"end":[58,77]}},"argument":{"annotation":{"meta":null,"sourceSpan":{"start":[58,76],"end":[58,77]}},"value":{"moduleName":null,"identifier":"n"},"type":"Var"},"type":"App","abstraction":{"annotation":{"meta":null,"sourceSpan":{"start":[58,26],"end":[58,75]}},"argument":{"annotation":{"meta":null,"sourceSpan":{"start":[58,69],"end":[58,75]}},"value":{"moduleName":null,"identifier":"digits"},"type":"Var"},"type":"App","abstraction":{"annotation":{"meta":null,"sourceSpan":{"start":[58,26],"end":[58,68]}},"argument":{"annotation":{"meta":{"metaType":"IsConstructor","identifiers":["value0"],"constructorType":"SumType"},"sourceSpan":{"start":[58,64],"end":[58,68]}},"value":{"moduleName":["Data","Maybe"],"identifier":"Just"},"type":"Var"},"type":"App","abstraction":{"annotation":{"meta":null,"sourceSpan":{"start":[58,26],"end":[58,63]}},"argument":{"annotation":{"meta":null,"sourceSpan":{"start":[58,49],"end":[58,62]}},"argument":{"annotation":{"meta":{"metaType":"IsConstructor","identifiers":[],"constructorType":"SumType"},"sourceSpan":{"start":[58,55],"end":[58,62]}},"value":{"moduleName":["Data","Maybe"],"identifier":"Nothing"},"type":"Var"},"type":"App","abstraction":{"annotation":{"meta":{"metaType":"IsForeign"},"sourceSpan":{"start":[58,49],"end":[58,54]}},"value":{"moduleName":["Data","Function"],"identifier":"const"},"type":"Var"}},"type":"App","abstraction":{"annotation":{"meta":null,"sourceSpan":{"start":[58,26],"end":[58,47]}},"argument":{"annotation":{"meta":{"metaType":"IsForeign"},"sourceSpan":{"start":[58,33],"end":[58,47]}},"value":{"moduleName":["Global"],"identifier":"_toExponential"},"type":"Var"},"type":"App","abstraction":{"annotation":{"meta":{"metaType":"IsForeign"},"sourceSpan":{"start":[58,26],"end":[58,32]}},"value":{"moduleName":["Data","Function","Uncurried"],"identifier":"runFn4"},"type":"Var"}}}}}},"argument":"n","type":"Abs"},"argument":"digits","type":"Abs"},"bindType":"NonRec"},{"annotation":{"meta":null,"sourceSpan":{"start":[92,1],"end":[92,45]}},"identifier":"encodeURIComponent","expression":{"annotation":{"meta":null,"sourceSpan":{"start":[92,1],"end":[92,45]}},"body":{"annotation":{"meta":null,"sourceSpan":{"start":[93,24],"end":[93,73]}},"argument":{"annotation":{"meta":null,"sourceSpan":{"start":[93,72],"end":[93,73]}},"value":{"moduleName":null,"identifier":"s"},"type":"Var"},"type":"App","abstraction":{"annotation":{"meta":null,"sourceSpan":{"start":[93,24],"end":[93,71]}},"argument":{"annotation":{"meta":{"metaType":"IsConstructor","identifiers":["value0"],"constructorType":"SumType"},"sourceSpan":{"start":[93,67],"end":[93,71]}},"value":{"moduleName":["Data","Maybe"],"identifier":"Just"},"type":"Var"},"type":"App","abstraction":{"annotation":{"meta":null,"sourceSpan":{"start":[93,24],"end":[93,66]}},"argument":{"annotation":{"meta":null,"sourceSpan":{"start":[93,52],"end":[93,65]}},"argument":{"annotation":{"meta":{"metaType":"IsConstructor","identifiers":[],"constructorType":"SumType"},"sourceSpan":{"start":[93,58],"end":[93,65]}},"value":{"moduleName":["Data","Maybe"],"identifier":"Nothing"},"type":"Var"},"type":"App","abstraction":{"annotation":{"meta":{"metaType":"IsForeign"},"sourceSpan":{"start":[93,52],"end":[93,57]}},"value":{"moduleName":["Data","Function"],"identifier":"const"},"type":"Var"}},"type":"App","abstraction":{"annotation":{"meta":null,"sourceSpan":{"start":[93,24],"end":[93,50]}},"argument":{"annotation":{"meta":{"metaType":"IsForeign"},"sourceSpan":{"start":[93,31],"end":[93,50]}},"value":{"moduleName":["Global"],"identifier":"_encodeURIComponent"},"type":"Var"},"type":"App","abstraction":{"annotation":{"meta":{"metaType":"IsForeign"},"sourceSpan":{"start":[93,24],"end":[93,30]}},"value":{"moduleName":["Data","Function","Uncurried"],"identifier":"runFn3"},"type":"Var"}}}}},"argument":"s","type":"Abs"},"bindType":"NonRec"},{"annotation":{"meta":null,"sourceSpan":{"start":[82,1],"end":[82,36]}},"identifier":"encodeURI","expression":{"annotation":{"meta":null,"sourceSpan":{"start":[82,1],"end":[82,36]}},"body":{"annotation":{"meta":null,"sourceSpan":{"start":[83,15],"end":[83,55]}},"argument":{"annotation":{"meta":null,"sourceSpan":{"start":[83,54],"end":[83,55]}},"value":{"moduleName":null,"identifier":"s"},"type":"Var"},"type":"App","abstraction":{"annotation":{"meta":null,"sourceSpan":{"start":[83,15],"end":[83,53]}},"argument":{"annotation":{"meta":{"metaType":"IsConstructor","identifiers":["value0"],"constructorType":"SumType"},"sourceSpan":{"start":[83,49],"end":[83,53]}},"value":{"moduleName":["Data","Maybe"],"identifier":"Just"},"type":"Var"},"type":"App","abstraction":{"annotation":{"meta":null,"sourceSpan":{"start":[83,15],"end":[83,48]}},"argument":{"annotation":{"meta":null,"sourceSpan":{"start":[83,34],"end":[83,47]}},"argument":{"annotation":{"meta":{"metaType":"IsConstructor","identifiers":[],"constructorType":"SumType"},"sourceSpan":{"start":[83,40],"end":[83,47]}},"value":{"moduleName":["Data","Maybe"],"identifier":"Nothing"},"type":"Var"},"type":"App","abstraction":{"annotation":{"meta":{"metaType":"IsForeign"},"sourceSpan":{"start":[83,34],"end":[83,39]}},"value":{"moduleName":["Data","Function"],"identifier":"const"},"type":"Var"}},"type":"App","abstraction":{"annotation":{"meta":null,"sourceSpan":{"start":[83,15],"end":[83,32]}},"argument":{"annotation":{"meta":{"metaType":"IsForeign"},"sourceSpan":{"start":[83,22],"end":[83,32]}},"value":{"moduleName":["Global"],"identifier":"_encodeURI"},"type":"Var"},"type":"App","abstraction":{"annotation":{"meta":{"metaType":"IsForeign"},"sourceSpan":{"start":[83,15],"end":[83,21]}},"value":{"moduleName":["Data","Function","Uncurried"],"identifier":"runFn3"},"type":"Var"}}}}},"argument":"s","type":"Abs"},"bindType":"NonRec"},{"annotation":{"meta":null,"sourceSpan":{"start":[87,1],"end":[87,45]}},"identifier":"decodeURIComponent","expression":{"annotation":{"meta":null,"sourceSpan":{"start":[87,1],"end":[87,45]}},"body":{"annotation":{"meta":null,"sourceSpan":{"start":[88,24],"end":[88,73]}},"argument":{"annotation":{"meta":null,"sourceSpan":{"start":[88,72],"end":[88,73]}},"value":{"moduleName":null,"identifier":"s"},"type":"Var"},"type":"App","abstraction":{"annotation":{"meta":null,"sourceSpan":{"start":[88,24],"end":[88,71]}},"argument":{"annotation":{"meta":{"metaType":"IsConstructor","identifiers":["value0"],"constructorType":"SumType"},"sourceSpan":{"start":[88,67],"end":[88,71]}},"value":{"moduleName":["Data","Maybe"],"identifier":"Just"},"type":"Var"},"type":"App","abstraction":{"annotation":{"meta":null,"sourceSpan":{"start":[88,24],"end":[88,66]}},"argument":{"annotation":{"meta":null,"sourceSpan":{"start":[88,52],"end":[88,65]}},"argument":{"annotation":{"meta":{"metaType":"IsConstructor","identifiers":[],"constructorType":"SumType"},"sourceSpan":{"start":[88,58],"end":[88,65]}},"value":{"moduleName":["Data","Maybe"],"identifier":"Nothing"},"type":"Var"},"type":"App","abstraction":{"annotation":{"meta":{"metaType":"IsForeign"},"sourceSpan":{"start":[88,52],"end":[88,57]}},"value":{"moduleName":["Data","Function"],"identifier":"const"},"type":"Var"}},"type":"App","abstraction":{"annotation":{"meta":null,"sourceSpan":{"start":[88,24],"end":[88,50]}},"argument":{"annotation":{"meta":{"metaType":"IsForeign"},"sourceSpan":{"start":[88,31],"end":[88,50]}},"value":{"moduleName":["Global"],"identifier":"_decodeURIComponent"},"type":"Var"},"type":"App","abstraction":{"annotation":{"meta":{"metaType":"IsForeign"},"sourceSpan":{"start":[88,24],"end":[88,30]}},"value":{"moduleName":["Data","Function","Uncurried"],"identifier":"runFn3"},"type":"Var"}}}}},"argument":"s","type":"Abs"},"bindType":"NonRec"},{"annotation":{"meta":null,"sourceSpan":{"start":[77,1],"end":[77,36]}},"identifier":"decodeURI","expression":{"annotation":{"meta":null,"sourceSpan":{"start":[77,1],"end":[77,36]}},"body":{"annotation":{"meta":null,"sourceSpan":{"start":[78,15],"end":[78,55]}},"argument":{"annotation":{"meta":null,"sourceSpan":{"start":[78,54],"end":[78,55]}},"value":{"moduleName":null,"identifier":"s"},"type":"Var"},"type":"App","abstraction":{"annotation":{"meta":null,"sourceSpan":{"start":[78,15],"end":[78,53]}},"argument":{"annotation":{"meta":{"metaType":"IsConstructor","identifiers":["value0"],"constructorType":"SumType"},"sourceSpan":{"start":[78,49],"end":[78,53]}},"value":{"moduleName":["Data","Maybe"],"identifier":"Just"},"type":"Var"},"type":"App","abstraction":{"annotation":{"meta":null,"sourceSpan":{"start":[78,15],"end":[78,48]}},"argument":{"annotation":{"meta":null,"sourceSpan":{"start":[78,34],"end":[78,47]}},"argument":{"annotation":{"meta":{"metaType":"IsConstructor","identifiers":[],"constructorType":"SumType"},"sourceSpan":{"start":[78,40],"end":[78,47]}},"value":{"moduleName":["Data","Maybe"],"identifier":"Nothing"},"type":"Var"},"type":"App","abstraction":{"annotation":{"meta":{"metaType":"IsForeign"},"sourceSpan":{"start":[78,34],"end":[78,39]}},"value":{"moduleName":["Data","Function"],"identifier":"const"},"type":"Var"}},"type":"App","abstraction":{"annotation":{"meta":null,"sourceSpan":{"start":[78,15],"end":[78,32]}},"argument":{"annotation":{"meta":{"metaType":"IsForeign"},"sourceSpan":{"start":[78,22],"end":[78,32]}},"value":{"moduleName":["Global"],"identifier":"_decodeURI"},"type":"Var"},"type":"App","abstraction":{"annotation":{"meta":{"metaType":"IsForeign"},"sourceSpan":{"start":[78,15],"end":[78,21]}},"value":{"moduleName":["Data","Function","Uncurried"],"identifier":"runFn3"},"type":"Var"}}}}},"argument":"s","type":"Abs"},"bindType":"NonRec"}],"comments":[{"LineComment":" | This module defines types for some global Javascript functions"},{"LineComment":" | and values."}],"foreign":["nan","isNaN","infinity","isFinite","readInt","readFloat","_toFixed","_toExponential","_toPrecision","_decodeURI","_encodeURI","_decodeURIComponent","_encodeURIComponent"],"sourceSpan":{"start":[3,1],"end":[93,73]}}